odoo9_addon_stock_picking_variant_mgmt-9.0.1.0.0-py2.7-nspkg.pth
odoo_addons/stock_picking_variant_mgmt/__openerp__.py
odoo_addons/stock_picking_variant_mgmt/__init__.py
odoo_addons/stock_picking_variant_mgmt/README.rst
odoo_addons/stock_picking_variant_mgmt/models/stock_move.py
odoo_addons/stock_picking_variant_mgmt/models/__init__.py
odoo_addons/stock_picking_variant_mgmt/wizard/stock_manage_variant.py
odoo_addons/stock_picking_variant_mgmt/wizard/stock_transfer_manage_variant_view.xml
odoo_addons/stock_picking_variant_mgmt/wizard/stock_manage_variant_view.xml
odoo_addons/stock_picking_variant_mgmt/wizard/__init__.py
odoo_addons/stock_picking_variant_mgmt/wizard/stock_transfer_manage_variant.py
odoo_addons/stock_picking_variant_mgmt/views/stock_picking_view.xml
odoo_addons/stock_picking_variant_mgmt/tests/test_stock_picking_variant_mgmt.py
odoo_addons/stock_picking_variant_mgmt/tests/__init__.py
odoo_addons/stock_picking_variant_mgmt/static/description/icon.png
odoo9_addon_stock_picking_variant_mgmt-9.0.1.0.0.dist-info/top_level.txt
odoo9_addon_stock_picking_variant_mgmt-9.0.1.0.0.dist-info/WHEEL
odoo9_addon_stock_picking_variant_mgmt-9.0.1.0.0.dist-info/RECORD
odoo9_addon_stock_picking_variant_mgmt-9.0.1.0.0.dist-info/metadata.json
odoo9_addon_stock_picking_variant_mgmt-9.0.1.0.0.dist-info/DESCRIPTION.rst
odoo9_addon_stock_picking_variant_mgmt-9.0.1.0.0.dist-info/METADATA
odoo9_addon_stock_picking_variant_mgmt-9.0.1.0.0.dist-info/namespace_packages.txt
