Metadata-Version: 2.0
Name: odoo9-addon-stock-picking-variant-mgmt
Version: 9.0.1.0.0
Summary: Handle the addition/removal of multiple variants and the quantities transferred in the Pickings.
Home-page: https://www.tecnativa.com
Author: Tecnativa,Odoo Community Association (OCA)
Author-email: support@odoo-community.org
License: AGPL-3
Platform: UNKNOWN
Requires-Dist: odoo (<9.1a,>=9.0a)
Requires-Dist: odoo9-addon-web-widget-x2many-2d-matrix
Classifier: Programming Language :: Python :: 2.7
Classifier: Framework :: Odoo
Classifier: License :: OSI Approved :: GNU Affero General Public License v3
